{
    "rating": -1.4946292763876414, 
    "name": "David", 
    "matches": [
        {
            "P1SkillCH": 7.881405258020575, 
            "winner": "Wing", 
            "Player2": "David", 
            "Player1": "Wing", 
            "P2SkillCH": -0.910258781977749, 
            "DATE": "10/10/2014 00:00:00"
        }, 
        {
            "P1SkillCH": 6.471769375222614, 
            "winner": "Mac", 
            "Player2": "David", 
            "Player1": "Mac", 
            "P2SkillCH": -0.881930911244261, 
            "DATE": "10/10/2014 00:00:00"
        }, 
        {
            "P1SkillCH": 0.16424402255050197, 
            "winner": "Bronte", 
            "Player2": "Bronte", 
            "Player1": "David", 
            "P2SkillCH": 2.111115412344482, 
            "DATE": "11/07/2014 00:00:00"
        }, 
        {
            "P1SkillCH": 0.13331639428386666, 
            "winner": "Mold", 
            "Player2": "Mold", 
            "Player1": "David", 
            "P2SkillCH": 2.0275485261505963, 
            "DATE": "11/07/2014 00:00:00"
        }
    ], 
    "wins": 0, 
    "num_tourneys": 2, 
    "game": "pm", 
    "games": 4, 
    "tournaments": [
        "10/10/2014 00:00:00", 
        "11/07/2014 00:00:00"
    ]
}