{
    "Date": "05/01/2015 00:00:00", 
    "Matches": [
        {
            "P1SkillCH": 0, 
            "winner": "Fox", 
            "number": "0", 
            "rnd": "1", 
            "Player2": "BYE", 
            "Player1": "Fox", 
            "P2SkillCH": 0, 
            "winners": "True"
        }, 
        {
            "P1SkillCH": -0.3747073623757533, 
            "winner": "Gavin", 
            "number": "1", 
            "rnd": "1", 
            "Player2": "Gavin", 
            "Player1": "Raymond", 
            "P2SkillCH": 0.7587734473493768, 
            "winners": "True"
        }, 
        {
            "P1SkillCH": 0, 
            "winner": "Thundrio", 
            "number": "2", 
            "rnd": "1", 
            "Player2": "BYE", 
            "Player1": "Thundrio", 
            "P2SkillCH": 0, 
            "winners": "True"
        }, 
        {
            "P1SkillCH": 0, 
            "winner": "deLee", 
            "number": "3", 
            "rnd": "1", 
            "Player2": "BYE", 
            "Player1": "deLee", 
            "P2SkillCH": 0, 
            "winners": "True"
        }, 
        {
            "P1SkillCH": 0, 
            "winner": "Agent", 
            "number": "4", 
            "rnd": "1", 
            "Player2": "BYE", 
            "Player1": "Agent", 
            "P2SkillCH": 0, 
            "winners": "True"
        }, 
        {
            "P1SkillCH": 0, 
            "winner": "Onward to the Edge", 
            "number": "5", 
            "rnd": "1", 
            "Player2": "BYE", 
            "Player1": "Onward to the Edge", 
            "P2SkillCH": 0, 
            "winners": "True"
        }, 
        {
            "P1SkillCH": 0, 
            "winner": "Brandon-chan", 
            "number": "6", 
            "rnd": "1", 
            "Player2": "BYE", 
            "Player1": "Brandon-chan", 
            "P2SkillCH": 0, 
            "winners": "True"
        }, 
        {
            "P1SkillCH": 0, 
            "winner": "Glaze", 
            "number": "7", 
            "rnd": "1", 
            "Player2": "BYE", 
            "Player1": "Glaze", 
            "P2SkillCH": 0, 
            "winners": "True"
        }, 
        {
            "P1SkillCH": 0, 
            "winner": "Lens", 
            "number": "8", 
            "rnd": "1", 
            "Player2": "BYE", 
            "Player1": "Lens", 
            "P2SkillCH": 0, 
            "winners": "True"
        }, 
        {
            "P1SkillCH": 0.19165435574990575, 
            "winner": "Jazz", 
            "number": "9", 
            "rnd": "1", 
            "Player2": "Jazz", 
            "Player1": "Silent", 
            "P2SkillCH": 0.07571229120322442, 
            "winners": "True"
        }, 
        {
            "P1SkillCH": 0, 
            "winner": "Mort", 
            "number": "10", 
            "rnd": "1", 
            "Player2": "BYE", 
            "Player1": "Mort", 
            "P2SkillCH": 0, 
            "winners": "True"
        }, 
        {
            "P1SkillCH": 0, 
            "winner": "Puddles", 
            "number": "11", 
            "rnd": "1", 
            "Player2": "BYE", 
            "Player1": "Puddles", 
            "P2SkillCH": 0, 
            "winners": "True"
        }, 
        {
            "P1SkillCH": 0, 
            "winner": "This", 
            "number": "12", 
            "rnd": "1", 
            "Player2": "BYE", 
            "Player1": "This", 
            "P2SkillCH": 0, 
            "winners": "True"
        }, 
        {
            "P1SkillCH": 2.4102695688738685, 
            "winner": "Madvillain", 
            "number": "13", 
            "rnd": "1", 
            "Player2": "LiquidBrick", 
            "Player1": "Madvillain", 
            "P2SkillCH": -1.7171182433850731, 
            "winners": "True"
        }, 
        {
            "P1SkillCH": 0, 
            "winner": "Bronte", 
            "number": "14", 
            "rnd": "1", 
            "Player2": "BYE", 
            "Player1": "Bronte", 
            "P2SkillCH": 0, 
            "winners": "True"
        }, 
        {
            "P1SkillCH": 0, 
            "winner": "Jerk", 
            "number": "15", 
            "rnd": "1", 
            "Player2": "BYE", 
            "Player1": "Jerk", 
            "P2SkillCH": 0, 
            "winners": "True"
        }, 
        {
            "P1SkillCH": -0.005542044536184676, 
            "winner": "Fox", 
            "number": "16", 
            "rnd": "2", 
            "Player2": "Gavin", 
            "Player1": "Fox", 
            "P2SkillCH": -0.00066303415157698, 
            "winners": "True"
        }, 
        {
            "P1SkillCH": 0.5998860778600594, 
            "winner": "Thundrio", 
            "number": "17", 
            "rnd": "2", 
            "Player2": "deLee", 
            "Player1": "Thundrio", 
            "P2SkillCH": -0.3446579070032776, 
            "winners": "True"
        }, 
        {
            "P1SkillCH": 0.0014771325559976844, 
            "winner": "Agent", 
            "number": "18", 
            "rnd": "2", 
            "Player2": "Onward to the Edge", 
            "Player1": "Agent", 
            "P2SkillCH": 0.010134251534251959, 
            "winners": "True"
        }, 
        {
            "P1SkillCH": 0.006562522152812278, 
            "winner": "Brandon-chan", 
            "number": "19", 
            "rnd": "2", 
            "Player2": "Glaze", 
            "Player1": "Brandon-chan", 
            "P2SkillCH": 0.002647259948222569, 
            "winners": "True"
        }, 
        {
            "P1SkillCH": 0.007656366914233104, 
            "winner": "Lens", 
            "number": "20", 
            "rnd": "2", 
            "Player2": "Jazz", 
            "Player1": "Lens", 
            "P2SkillCH": -0.0070201884179112994, 
            "winners": "True"
        }, 
        {
            "P1SkillCH": 0.12242919716238276, 
            "winner": "Mort", 
            "number": "21", 
            "rnd": "2", 
            "Player2": "Puddles", 
            "Player1": "Mort", 
            "P2SkillCH": 1.2491298883208017, 
            "winners": "True"
        }, 
        {
            "P1SkillCH": 0.0008737021636235909, 
            "winner": "This", 
            "number": "22", 
            "rnd": "2", 
            "Player2": "Madvillain", 
            "Player1": "This", 
            "P2SkillCH": 0.0026576794155452887, 
            "winners": "True"
        }, 
        {
            "P1SkillCH": 0.0819035390806846, 
            "winner": "Bronte", 
            "number": "23", 
            "rnd": "2", 
            "Player2": "Jerk", 
            "Player1": "Bronte", 
            "P2SkillCH": 1.3095731641474835, 
            "winners": "True"
        }, 
        {
            "P1SkillCH": 0.007642235954790522, 
            "winner": "Fox", 
            "number": "24", 
            "rnd": "3", 
            "Player2": "Thundrio", 
            "Player1": "Fox", 
            "P2SkillCH": -0.008089561194697836, 
            "winners": "True"
        }, 
        {
            "P1SkillCH": 0.295499167756347, 
            "winner": "Agent", 
            "number": "25", 
            "rnd": "3", 
            "Player2": "Brandon-chan", 
            "Player1": "Agent", 
            "P2SkillCH": -0.19562890872534666, 
            "winners": "True"
        }, 
        {
            "P1SkillCH": 0.07399742009348387, 
            "winner": "Lens", 
            "number": "26", 
            "rnd": "3", 
            "Player2": "Mort", 
            "Player1": "Lens", 
            "P2SkillCH": -0.0569763430823258, 
            "winners": "True"
        }, 
        {
            "P1SkillCH": 0.16992343659206455, 
            "winner": "This", 
            "number": "27", 
            "rnd": "3", 
            "Player2": "Bronte", 
            "Player1": "This", 
            "P2SkillCH": -0.11860635726792879, 
            "winners": "True"
        }, 
        {
            "P1SkillCH": 0.12842342589540579, 
            "winner": "Fox", 
            "number": "28", 
            "rnd": "4", 
            "Player2": "Agent", 
            "Player1": "Fox", 
            "P2SkillCH": -0.08394883054403834, 
            "winners": "True"
        }, 
        {
            "P1SkillCH": -0.22894596642049692, 
            "winner": "This", 
            "number": "29", 
            "rnd": "4", 
            "Player2": "This", 
            "Player1": "Lens", 
            "P2SkillCH": 0.34241927034515385, 
            "winners": "True"
        }, 
        {
            "P1SkillCH": 0.12952127750759956, 
            "winner": "Fox", 
            "number": "30", 
            "rnd": "5", 
            "Player2": "This", 
            "Player1": "Fox", 
            "P2SkillCH": -0.0786841582452027, 
            "winners": "True"
        }, 
        {
            "P1SkillCH": 0, 
            "winner": "Raymond", 
            "number": "32", 
            "rnd": "-1", 
            "Player2": "Raymond", 
            "Player1": "BYE", 
            "P2SkillCH": 0, 
            "winners": "False"
        }, 
        {
            "P1SkillCH": 0, 
            "winner": "BYE", 
            "number": "33", 
            "rnd": "-1", 
            "Player2": "BYE", 
            "Player1": "BYE", 
            "P2SkillCH": 0, 
            "winners": "False"
        }, 
        {
            "P1SkillCH": 0, 
            "winner": "BYE", 
            "number": "34", 
            "rnd": "-1", 
            "Player2": "BYE", 
            "Player1": "BYE", 
            "P2SkillCH": 0, 
            "winners": "False"
        }, 
        {
            "P1SkillCH": 0, 
            "winner": "BYE", 
            "number": "35", 
            "rnd": "-1", 
            "Player2": "BYE", 
            "Player1": "BYE", 
            "P2SkillCH": 0, 
            "winners": "False"
        }, 
        {
            "P1SkillCH": 0, 
            "winner": "Silent", 
            "number": "36", 
            "rnd": "-1", 
            "Player2": "Silent", 
            "Player1": "BYE", 
            "P2SkillCH": 0, 
            "winners": "False"
        }, 
        {
            "P1SkillCH": 0, 
            "winner": "BYE", 
            "number": "37", 
            "rnd": "-1", 
            "Player2": "BYE", 
            "Player1": "BYE", 
            "P2SkillCH": 0, 
            "winners": "False"
        }, 
        {
            "P1SkillCH": 0, 
            "winner": "LiquidBrick", 
            "number": "38", 
            "rnd": "-1", 
            "Player2": "LiquidBrick", 
            "Player1": "BYE", 
            "P2SkillCH": 0, 
            "winners": "False"
        }, 
        {
            "P1SkillCH": 0, 
            "winner": "BYE", 
            "number": "39", 
            "rnd": "-1", 
            "Player2": "BYE", 
            "Player1": "BYE", 
            "P2SkillCH": 0, 
            "winners": "False"
        }, 
        {
            "P1SkillCH": 3.219599301592737, 
            "winner": "Raymond", 
            "number": "40", 
            "rnd": "-2", 
            "Player2": "Onward to the Edge", 
            "Player1": "Raymond", 
            "P2SkillCH": -0.6128867834264344, 
            "winners": "False"
        }, 
        {
            "P1SkillCH": 0, 
            "winner": "Glaze", 
            "number": "41", 
            "rnd": "-2", 
            "Player2": "Glaze", 
            "Player1": "BYE", 
            "P2SkillCH": 0, 
            "winners": "False"
        }, 
        {
            "P1SkillCH": 0, 
            "winner": "Gavin", 
            "number": "42", 
            "rnd": "-2", 
            "Player2": "Gavin", 
            "Player1": "BYE", 
            "P2SkillCH": 0, 
            "winners": "False"
        }, 
        {
            "P1SkillCH": 0, 
            "winner": "deLee", 
            "number": "43", 
            "rnd": "-2", 
            "Player2": "deLee", 
            "Player1": "BYE", 
            "P2SkillCH": 0, 
            "winners": "False"
        }, 
        {
            "P1SkillCH": 0.11713285805060814, 
            "winner": "Madvillain", 
            "number": "44", 
            "rnd": "-2", 
            "Player2": "Madvillain", 
            "Player1": "Silent", 
            "P2SkillCH": 0.33181361897486106, 
            "winners": "False"
        }, 
        {
            "P1SkillCH": 0, 
            "winner": "Jerk", 
            "number": "45", 
            "rnd": "-2", 
            "Player2": "Jerk", 
            "Player1": "BYE", 
            "P2SkillCH": 0, 
            "winners": "False"
        }, 
        {
            "P1SkillCH": 1.0418922467482012, 
            "winner": "LiquidBrick", 
            "number": "46", 
            "rnd": "-2", 
            "Player2": "Jazz", 
            "Player1": "LiquidBrick", 
            "P2SkillCH": -0.23673153223240817, 
            "winners": "False"
        }, 
        {
            "P1SkillCH": 0, 
            "winner": "Puddles", 
            "number": "47", 
            "rnd": "-2", 
            "Player2": "Puddles", 
            "Player1": "BYE", 
            "P2SkillCH": 0, 
            "winners": "False"
        }, 
        {
            "P1SkillCH": -0.583255131752134, 
            "winner": "Glaze", 
            "number": "48", 
            "rnd": "-3", 
            "Player2": "Glaze", 
            "Player1": "Raymond", 
            "P2SkillCH": 0.8761039045714725, 
            "winners": "False"
        }, 
        {
            "P1SkillCH": -0.1555109687485281, 
            "winner": "deLee", 
            "number": "49", 
            "rnd": "-3", 
            "Player2": "deLee", 
            "Player1": "Gavin", 
            "P2SkillCH": 0.27784339915650946, 
            "winners": "False"
        }, 
        {
            "P1SkillCH": 0.7182571485991041, 
            "winner": "Madvillain", 
            "number": "50", 
            "rnd": "-3", 
            "Player2": "Jerk", 
            "Player1": "Madvillain", 
            "P2SkillCH": -0.5988112293752685, 
            "winners": "False"
        }, 
        {
            "P1SkillCH": 0, 
            "winner": "LiquidBrick", 
            "number": "51", 
            "rnd": "-3", 
            "Player2": "BYE", 
            "Player1": "LiquidBrick", 
            "P2SkillCH": 0, 
            "winners": "False"
        }, 
        {
            "P1SkillCH": 2.1162301737527915, 
            "winner": "Glaze", 
            "number": "52", 
            "rnd": "-4", 
            "Player2": "Mort", 
            "Player1": "Glaze", 
            "P2SkillCH": -0.6586892753025708, 
            "winners": "False"
        }, 
        {
            "P1SkillCH": -0.1075137733759135, 
            "winner": "Bronte", 
            "number": "53", 
            "rnd": "-4", 
            "Player2": "Bronte", 
            "Player1": "deLee", 
            "P2SkillCH": 0.1524460675231296, 
            "winners": "False"
        }, 
        {
            "P1SkillCH": 1.6527416978469631, 
            "winner": "Madvillain", 
            "number": "54", 
            "rnd": "-4", 
            "Player2": "Thundrio", 
            "Player1": "Madvillain", 
            "P2SkillCH": -0.5760657736269437, 
            "winners": "False"
        }, 
        {
            "P1SkillCH": -0.05143986060486938, 
            "winner": "Brandon-chan", 
            "number": "55", 
            "rnd": "-4", 
            "Player2": "Brandon-chan", 
            "Player1": "LiquidBrick", 
            "P2SkillCH": 0.08625261345706292, 
            "winners": "False"
        }, 
        {
            "P1SkillCH": -0.023480775162116885, 
            "winner": "Bronte", 
            "number": "56", 
            "rnd": "-5", 
            "Player2": "Bronte", 
            "Player1": "Glaze", 
            "P2SkillCH": 0.053215620454786006, 
            "winners": "False"
        }, 
        {
            "P1SkillCH": -0.002365124842764743, 
            "winner": "Brandon-chan", 
            "number": "57", 
            "rnd": "-5", 
            "Player2": "Brandon-chan", 
            "Player1": "Madvillain", 
            "P2SkillCH": 0.016400746871013894, 
            "winners": "False"
        }, 
        {
            "P1SkillCH": -0.11331849430719743, 
            "winner": "Agent", 
            "number": "58", 
            "rnd": "-6", 
            "Player2": "Agent", 
            "Player1": "Bronte", 
            "P2SkillCH": 0.18629676499809023, 
            "winners": "False"
        }, 
        {
            "P1SkillCH": 0.4172161830131671, 
            "winner": "Brandon-chan", 
            "number": "59", 
            "rnd": "-6", 
            "Player2": "Lens", 
            "Player1": "Brandon-chan", 
            "P2SkillCH": -0.23319371569751013, 
            "winners": "False"
        }, 
        {
            "P1SkillCH": -0.19758544663706346, 
            "winner": "Brandon-chan", 
            "number": "60", 
            "rnd": "-7", 
            "Player2": "Brandon-chan", 
            "Player1": "Agent", 
            "P2SkillCH": 0.3078062164908886, 
            "winners": "False"
        }, 
        {
            "P1SkillCH": -0.1836738556815476, 
            "winner": "This", 
            "number": "61", 
            "rnd": "-8", 
            "Player2": "This", 
            "Player1": "Brandon-chan", 
            "P2SkillCH": 0.24152486463757583, 
            "winners": "False"
        }, 
        {
            "P1SkillCH": 0.1272938496599636, 
            "winner": "Fox", 
            "number": "62", 
            "rnd": "6", 
            "Player2": "This", 
            "Player1": "Fox", 
            "P2SkillCH": -0.07691405673060814, 
            "winners": "True"
        }
    ], 
    "Game": "pm", 
    "Entrants": [
        {
            "wins": 0, 
            "place": 1, 
            "rankchange": 0, 
            "name": "Jerk", 
            "fakewins": 0
        }, 
        {
            "wins": 0, 
            "place": 1, 
            "rankchange": 1, 
            "name": "Onward to the Edge", 
            "fakewins": 0
        }, 
        {
            "wins": 0, 
            "place": 1, 
            "rankchange": 0, 
            "name": "Puddles", 
            "fakewins": 0
        }, 
        {
            "wins": 0, 
            "place": 1, 
            "rankchange": 2, 
            "name": "Silent", 
            "fakewins": 0
        }, 
        {
            "wins": 1, 
            "place": 1, 
            "rankchange": 2, 
            "name": "deLee", 
            "fakewins": 1
        }, 
        {
            "wins": 1, 
            "place": 1, 
            "rankchange": -1, 
            "name": "Gavin", 
            "fakewins": 1
        }, 
        {
            "wins": 1, 
            "place": 1, 
            "rankchange": 1, 
            "name": "Jazz", 
            "fakewins": 1
        }, 
        {
            "wins": 1, 
            "place": 1, 
            "rankchange": 0, 
            "name": "Mort", 
            "fakewins": 1
        }, 
        {
            "wins": 1, 
            "place": 1, 
            "rankchange": 2, 
            "name": "Raymond", 
            "fakewins": 1
        }, 
        {
            "wins": 1, 
            "place": 1, 
            "rankchange": 2, 
            "name": "Thundrio", 
            "fakewins": 1
        }, 
        {
            "wins": 1, 
            "place": 1, 
            "rankchange": 1, 
            "name": "LiquidBrick", 
            "fakewins": 1
        }, 
        {
            "wins": 2, 
            "place": 1, 
            "rankchange": 4, 
            "name": "Glaze", 
            "fakewins": 2
        }, 
        {
            "wins": 2, 
            "place": 1, 
            "rankchange": 0, 
            "name": "Lens", 
            "fakewins": 2
        }, 
        {
            "wins": 3, 
            "place": 1, 
            "rankchange": 0, 
            "name": "Agent", 
            "fakewins": 3
        }, 
        {
            "wins": 3, 
            "place": 1, 
            "rankchange": 0, 
            "name": "Bronte", 
            "fakewins": 3
        }, 
        {
            "wins": 4, 
            "place": 1, 
            "rankchange": 5, 
            "name": "Madvillain", 
            "fakewins": 4
        }, 
        {
            "wins": 4, 
            "place": 1, 
            "rankchange": 0, 
            "name": "This", 
            "fakewins": 4
        }, 
        {
            "wins": 5, 
            "place": 1, 
            "rankchange": 0, 
            "name": "Brandon-chan", 
            "fakewins": 5
        }, 
        {
            "wins": 5, 
            "place": 1, 
            "rankchange": 0, 
            "name": "Fox", 
            "fakewins": 5
        }
    ], 
    "g": "pm"
}