{
	"date":"10/15",
	"location":"Courtyard",
	"city":"Harrenhall",
	"results":
	[
		{
			"place":1,
			"name":"Jimmy the Hand",
			"id":"jimmyhand",
			"eloshift":150
		},
		{
			"place":2,
			"name":"The Hound",
			"id":"clegane",
			"eloshift":78
		},

		{
			"place":3,
			"name":"Harry Potter",
			"id":"potter",
			"eloshift":100
		},

		{			
			"place":4,
			"name":"Elvis",
			"id":"elvis",
			"eloshift":30
		},

		{
			"place":5,
			"name":"Jace the Mind Sculptor",
			"id":"jace",
			"eloshift":-15
		},

		{
			"place":5,
			"name":"Mickey Mouse",
			"id":"mickey",
			"eloshift":50
		},

		{
			"place":7,
			"name":"Arya Stark",
			"id":"arya",
			"eloshift":0
		},

		{
			"place":7,
			"name":"James and the Giant PEach",
			"id":"arya",
			"eloshift":0
		},

		{
			"place":9,
			"name":"Batgirl",
			"id":"batgirl",
			"eloshift":-20
		},

		{
			"place":9,
			"name":"Brian Kibler",
			"id":"kibler",
			"eloshift":-30
		},

		{
			"place":9,
			"name":"Frau d' lent",
			"id":"fraudlent",
			"eloshift":-50
		}
]
	}
